iaparc_inference/__init__.py
iaparc_inference/config.py
iaparc_inference/data_decoder.py
iaparc_inference/data_encoder.py
iaparc_inference/decoders.py
iaparc_inference/encoders.py
iaparc_inference/job_handler.py
iaparc_inference/listener.py
iaparc_inference/subscription.py
iaparc_inference-0.6.5.dist-info/LICENSE
iaparc_inference-0.6.5.dist-info/METADATA
iaparc_inference-0.6.5.dist-info/WHEEL
iaparc_inference-0.6.5.dist-info/top_level.txt
iaparc_inference-0.6.5.dist-info/RECORD
