Metadata-Version: 2.2
Name: iaparc_inference
Version: 0.6.5
Summary: Inference service package for IAPARC
Author-email: Bertrand Louargant <blouargant@chapsvision.com>
Project-URL: Homepage, https://gitlab.com/ia-parc/public/pypi/iaparc_inference
Project-URL: Issues, https://gitlab.com/ia-parc/public/pypi/iaparc_inference/issues
Classifier: Programming Language :: Python :: 3
Classifier: License :: OSI Approved :: Apache Software License
Classifier: Operating System :: OS Independent
Requires-Python: >=3.8
License-File: LICENSE
Requires-Dist: nats-py~=2.9.0
Requires-Dist: pillow~=10.4.0
Requires-Dist: pyyaml~=6.0.2
Requires-Dist: asyncio~=3.4.3
Requires-Dist: json-tricks~=3.17.3
Requires-Dist: streaming_form_data~=1.16.0
Requires-Dist: urllib3~=2.2.3
